__init__.py
openocr.py
OpenOCR-0.1.0.dist-info/LICENSE
OpenOCR-0.1.0.dist-info/METADATA
OpenOCR-0.1.0.dist-info/WHEEL
OpenOCR-0.1.0.dist-info/top_level.txt
OpenOCR-0.1.0.dist-info/RECORD
